wisely/__init__.py
wisely/googlekms.py
wisely-0.3.dist-info/DESCRIPTION.rst
wisely-0.3.dist-info/METADATA
wisely-0.3.dist-info/RECORD
wisely-0.3.dist-info/WHEEL
wisely-0.3.dist-info/entry_points.txt
wisely-0.3.dist-info/metadata.json
wisely-0.3.dist-info/top_level.txt
