Metadata-Version: 2.0
Name: wisely
Version: 0.3
Summary: Simple secrets store for Google Cloud
Home-page: https://github.com/mlaferrera/wisely
Author: Marcus LaFerrera
Author-email: marcus@randomhack.org
License: MIT
Keywords: secrets management,google cloud,google kms
Platform: UNKNOWN
Requires-Python: >=3.5
Requires-Dist: python-magic
Requires-Dist: google-api-python-client
Requires-Dist: google-cloud-storage
Requires-Dist: google-auth-httplib2
